nunpy/__init__.py
nunpy_utils-0.0.1.3.dist-info/licenses/LICENSE
nunpy_utils-0.0.1.3.dist-info/METADATA
nunpy_utils-0.0.1.3.dist-info/WHEEL
nunpy_utils-0.0.1.3.dist-info/top_level.txt
nunpy_utils-0.0.1.3.dist-info/RECORD
